magic_tools/__init__.py
magic_tools/one_operation.py
magic_tools-0.1.3.dist-info/licenses/LICENSE
magic_tools-0.1.3.dist-info/METADATA
magic_tools-0.1.3.dist-info/WHEEL
magic_tools-0.1.3.dist-info/top_level.txt
magic_tools-0.1.3.dist-info/RECORD
