Metadata-Version: 2.4
Name: magic-tools
Version: 0.1.3
Summary: Python daily widgets
Author-email: Muieay <muieay@example.com>
License:                                  Apache License
Project-URL: Homepage, https://github.com/muieay/magic-tools
Project-URL: Bug Tracker, https://github.com/muieay/magic-tools/issues
Classifier: Programming Language :: Python :: 3
Classifier: Operating System :: OS Independent
Requires-Python: >=3.8
License-File: LICENSE
Dynamic: license-file
